quicksql/__init__.py
quicksql/__init__.pyi
quicksql/_quicksql.py
quicksql/py.typed
qsql-1.0.2.2.dist-info/licenses/LICENSE
qsql-1.0.2.2.dist-info/WHEEL
qsql-1.0.2.2.dist-info/METADATA
qsql-1.0.2.2.dist-info/RECORD
