Metadata-Version: 2.4
Name: qsql
Version: 1.0.2.2
Summary: Parses queries from an sql file, and turns them into callable f-strings. Also a file cache decorator for slow queries and multi-session permanence, supports async functions.
Author-email: Charles Marks <charlesmarksco@gmail.com>
Classifier: License :: OSI Approved :: MIT License
License-File: LICENSE
Requires-Dist: orjson
Project-URL: Home, https://github.com/CircuitCM/pyquicksql
